aws_profile_switch/__init__.py
aws_profile_switch/cli.py
aws_profile_switch/config_parser.py
aws_profile_switch/core.py
aws_profile_switch/exceptions.py
aws_profile_switch/models.py
aws_profile_switch/search.py
aws_profile_switch/shell.py
aws_profile_switch/ui.py
aws_profile_switch-0.1.5.dist-info/licenses/LICENSE
aws_profile_switch-0.1.5.dist-info/METADATA
aws_profile_switch-0.1.5.dist-info/WHEEL
aws_profile_switch-0.1.5.dist-info/entry_points.txt
aws_profile_switch-0.1.5.dist-info/top_level.txt
aws_profile_switch-0.1.5.dist-info/RECORD
