Metadata-Version: 2.4
Name: aws-profile-switch
Version: 0.1.5
Summary: An interactive CLI tool to easily switch AWS profiles, especially for IAM Identity Center (SSO) users.
Author-email: tamagokakedon <takedai0313@users.noreply.github.com>
License-Expression: MIT
Project-URL: Homepage, https://github.com/takedai0313/aws-profile-switch
Project-URL: Bug Tracker, https://github.com/takedai0313/aws-profile-switch/issues
Classifier: Programming Language :: Python :: 3
Classifier: Operating System :: OS Independent
Classifier: Environment :: Console
Classifier: Topic :: Utilities
Classifier: Intended Audience :: Developers
Classifier: Intended Audience :: System Administrators
Requires-Python: >=3.8
License-File: LICENSE
Requires-Dist: prompt-toolkit<4.0.0,>=3.0.0
Requires-Dist: fuzzywuzzy<1.0.0,>=0.18.0
Requires-Dist: python-Levenshtein<1.0.0,>=0.12.0
Dynamic: license-file
